{"id":"1:2","parent":{"id":"0:1"},"name":"Frame 1","removed":false,"visible":true,"locked":false,"opacity":1,"blendMode":"PASS_THROUGH","isMask":false,"effects":[],"effectStyleId":"","relativeTransform":[[1,0,-14],[0,1,-373]],"absoluteTransform":[[1,0,-14],[0,1,-373]],"x":-14,"y":-373,"width":500,"height":500,"rotation":0,"layoutAlign":"MIN","constrainProportions":false,"children":[{"id":"1:3","parent":{"id":"1:2"},"name":"Hello World!","removed":false,"visible":true,"locked":false,"opacity":1,"blendMode":"PASS_THROUGH","isMask":false,"effects":[],"effectStyleId":"","fills":[{"type":"SOLID","visible":true,"opacity":1,"blendMode":"NORMAL","color":{"r":0.09184032678604126,"g":0.12650001049041748,"b":0.9583333134651184}}],"fillStyleId":"","strokes":[],"strokeStyleId":"","strokeWeight":1,"strokeAlign":"OUTSIDE","strokeCap":"NONE","strokeJoin":"MITER","strokeMiterLimit":4,"dashPattern":[],"relativeTransform":[[1,0,153],[0,1,229]],"absoluteTransform":[[1,0,139],[0,1,-144]],"x":153,"y":229,"width":195,"height":42,"rotation":0,"layoutAlign":"MIN","constrainProportions":false,"exportSettings":[],"constraints":{"horizontal":"MIN","vertical":"MIN"},"textStyleId":"","characters":"Hello World!","hasMissingFont":false,"autoRename":true,"fontSize":36,"paragraphIndent":0,"paragraphSpacing":0,"textAlignHorizontal":"LEFT","textAlignVertical":"TOP","textCase":"ORIGINAL","textDecoration":"NONE","textAutoResize":"WIDTH_AND_HEIGHT","letterSpacing":{"unit":"PERCENT","value":0},"lineHeight":{"unit":"AUTO"},"fontName":{"family":"Roboto","style":"Regular"},"reactions":[],"type":"TEXT"}],"exportSettings":[],"fills":[{"type":"SOLID","visible":true,"opacity":1,"blendMode":"NORMAL","color":{"r":0.6666666865348816,"g":0.18611109256744385,"b":0.18611109256744385}}],"fillStyleId":"","strokes":[],"strokeStyleId":"","strokeWeight":1,"strokeAlign":"INSIDE","strokeCap":"NONE","strokeJoin":"MITER","strokeMiterLimit":4,"dashPattern":[],"cornerRadius":0,"cornerSmoothing":0,"topLeftRadius":0,"topRightRadius":0,"bottomLeftRadius":0,"bottomRightRadius":0,"layoutGrids":[],"gridStyleId":"","backgrounds":[{"type":"SOLID","visible":true,"opacity":1,"blendMode":"NORMAL","color":{"r":0.6666666865348816,"g":0.18611109256744385,"b":0.18611109256744385}}],"backgroundStyleId":"","clipsContent":true,"guides":[],"expanded":true,"constraints":{"horizontal":"MIN","vertical":"MIN"},"layoutMode":"NONE","counterAxisSizingMode":"FIXED","horizontalPadding":0,"verticalPadding":0,"itemSpacing":0,"overflowDirection":"NONE","numberOfFixedChildren":0,"overlayPositionType":"CENTER","overlayBackground":{"type":"NONE"},"overlayBackgroundInteraction":"NONE","reactions":[],"type":"FRAME"}